connexion_sql_utils/__init__.py
connexion_sql_utils/base_mixin_abc.py
connexion_sql_utils/crud.py
connexion_sql_utils/decorators.py
connexion_sql_utils/sqlmixins.py
connexion_sql_utils-0.1.4.dist-info/DESCRIPTION.rst
connexion_sql_utils-0.1.4.dist-info/METADATA
connexion_sql_utils-0.1.4.dist-info/RECORD
connexion_sql_utils-0.1.4.dist-info/WHEEL
connexion_sql_utils-0.1.4.dist-info/metadata.json
connexion_sql_utils-0.1.4.dist-info/top_level.txt
