Metadata-Version: 2.0
Name: connexion-sql-utils
Version: 0.1.4
Summary: Sqlalchemy, Postgres, Connexion utility
Home-page: https://github.com/m-housh/connexion_sql_utils
Author: Michael Housh
Author-email: mhoush@houshhomeenergy.com
License: MIT license
Keywords: connexion_sql_utils
Platform: UNKNOWN
Classifier: Development Status :: 2 - Pre-Alpha
Classifier: Intended Audience :: Developers
Classifier: License :: OSI Approved :: MIT License
Classifier: Natural Language :: English
Classifier: Programming Language :: Python :: 3.5
Classifier: Programming Language :: Python :: 3.6
Requires-Dist: connexion (==1.1.5)
Requires-Dist: psycopg2 (>=2.7)
Requires-Dist: sqlalchemy (>=1.1.6)
